proxybroker2/__init__.py
proxybroker2/__main__.py
proxybroker2/api.py
proxybroker2/checker.py
proxybroker2/cli.py
proxybroker2/data/GeoLite2-Country.mmdb
proxybroker2/data/__init__.py
proxybroker2/errors.py
proxybroker2/judge.py
proxybroker2/negotiators.py
proxybroker2/providers.py
proxybroker2/proxy.py
proxybroker2/resolver.py
proxybroker2/server.py
proxybroker2/utils.py
proxybroker2-2.0.0a4.dist-info/entry_points.txt
proxybroker2-2.0.0a4.dist-info/LICENSE
proxybroker2-2.0.0a4.dist-info/WHEEL
proxybroker2-2.0.0a4.dist-info/METADATA
proxybroker2-2.0.0a4.dist-info/RECORD
