Metadata-Version: 2.1
Name: proxybroker2
Version: 2.0.0a4
Summary: The New (auto rotate) Proxy [Finder | Checker | Server]. HTTP(S) & SOCKS.
Home-page: http://proxybroker.readthedocs.io/
License: Apache-2.0
Author: BlueT - Matthew Lien - 練喆明
Author-email: bluet@bluet.org
Requires-Python: >=3.8,<4.0
Classifier: Development Status :: 5 - Production/Stable
Classifier: Environment :: Console
Classifier: Environment :: Web Environment
Classifier: Intended Audience :: Developers
Classifier: License :: OSI Approved :: Apache Software License
Classifier: Operating System :: MacOS :: MacOS X
Classifier: Operating System :: Microsoft :: Windows
Classifier: Operating System :: POSIX
Classifier: Programming Language :: Python :: 3
Classifier: Programming Language :: Python :: 3.8
Classifier: Programming Language :: Python :: 3.9
Classifier: Programming Language :: Python :: 3.10
Classifier: Programming Language :: Python :: 3.11
Classifier: Programming Language :: Python :: 3.10
Classifier: Programming Language :: Python :: 3.8
Classifier: Programming Language :: Python :: 3.9
Classifier: Topic :: Internet :: Proxy Servers
Classifier: Topic :: Internet :: WWW/HTTP :: Indexing/Search
Requires-Dist: aiodns (>=3.0.0,<4.0.0)
Requires-Dist: aiohttp (>=3.8.1,<4.0.0)
Requires-Dist: attrs (>=22.1.0,<23.0.0)
Requires-Dist: cachetools (>=5.2.0,<6.0.0)
Requires-Dist: click (>=8.1.3,<9.0.0)
Requires-Dist: maxminddb (>=2.2.0,<3.0.0)
Project-URL: Documentation, http://proxybroker.readthedocs.io/
Project-URL: Repository, https://github.com/bluet/proxybroker2
